nalibsUtils/__base.py
nalibsUtils/__init__.py
nalibsUtils/__version.py
nalibsUtils/utils_csv.py
nalibsUtils/utils_files.py
nalibsUtils/utils_json.py
nalibsUtils/utils_yaml.py
nalibs_utils-0.1.2.dist-info/LICENSE
nalibs_utils-0.1.2.dist-info/METADATA
nalibs_utils-0.1.2.dist-info/WHEEL
nalibs_utils-0.1.2.dist-info/entry_points.txt
nalibs_utils-0.1.2.dist-info/top_level.txt
nalibs_utils-0.1.2.dist-info/RECORD
