Metadata-Version: 2.1
Name: nalibs-utils
Version: 0.1.2
Summary: qana - tiny package - nalibsUtils
Author-email: Ron <naq0310@gmail.com>
Maintainer-email: Ron <naq0310@gmail.com>
Project-URL: Homepage, https://github.com/pypa/sampleproject
Project-URL: Issues, https://github.com/pypa/sampleproject/issues
Classifier: Programming Language :: Python :: 3
Classifier: License :: OSI Approved :: MIT License
Classifier: Operating System :: OS Independent
Requires-Python: >=3.9
License-File: LICENSE
Requires-Dist: PyYAML
Requires-Dist: requests
